robot/__main__.py
RPA/application.py
RPA/Archive.py
RPA/Browser/__init__.py
RPA/Browser/common.py
RPA/Browser/Playwright.py
RPA/Browser/Selenium.py
RPA/Calendar.py
RPA/Cloud/Azure.py
RPA/Crypto.py
RPA/Database.py
RPA/Desktop/__init__.py
RPA/Desktop/Clipboard.py
RPA/Desktop/keywords/__init__.py
RPA/Desktop/keywords/application.py
RPA/Desktop/keywords/clipboard.py
RPA/Desktop/keywords/context.py
RPA/Desktop/keywords/finder.py
RPA/Desktop/keywords/keyboard.py
RPA/Desktop/keywords/mouse.py
RPA/Desktop/keywords/screen.py
RPA/Desktop/keywords/text.py
RPA/Desktop/OperatingSystem.py
RPA/Desktop/utils.py
RPA/Desktop/Windows.py
RPA/DocumentAI/__init__.py
RPA/DocumentAI/Base64AI.py
RPA/DocumentAI/DocumentAI.py
RPA/DocumentAI/Nanonets.py
RPA/Email/__init__.py
RPA/Email/common.py
RPA/Email/Exchange.py
RPA/Email/ImapSmtp.py
RPA/Excel/__init__.py
RPA/Excel/Application.py
RPA/Excel/Files.py
RPA/FileSystem.py
RPA/FTP.py
RPA/HTTP.py
RPA/Images.py
RPA/includes/__init__.py
RPA/includes/dialog_styles.css
RPA/JavaAccessBridge.py
RPA/JSON.py
RPA/MFA.py
RPA/MSGraph.py
RPA/Netsuite.py
RPA/Notifier.py
RPA/Outlook/__init__.py
RPA/Outlook/Application.py
RPA/Robocloud/__init__.py
RPA/Robocloud/Items.py
RPA/Robocloud/Secrets.py
RPA/Robocorp/__init__.py
RPA/Robocorp/Process.py
RPA/Robocorp/Storage.py
RPA/Robocorp/utils.py
RPA/Robocorp/Vault.py
RPA/Robocorp/WorkItems.py
RPA/RobotLogListener.py
RPA/Salesforce.py
RPA/SAP.py
RPA/scripts/crypto.py
RPA/scripts/robocorp_cloud.py
RPA/Slack.py
RPA/Smartsheet.py
RPA/Tables.py
RPA/Tasks.py
RPA/Twitter.py
RPA/version.py
RPA/Word/__init__.py
RPA/Word/Application.py
rpaframework-30.0.1.dist-info/entry_points.txt
rpaframework-30.0.1.dist-info/LICENSE
rpaframework-30.0.1.dist-info/METADATA
rpaframework-30.0.1.dist-info/WHEEL
rpaframework-30.0.1.dist-info/RECORD
